{
  "state" : {
    "ScoreBoard.Settings.Setting(ScoreBoard.Operator.Llama.KeyControl.StartJam)" : "q",
    "ScoreBoard.Settings.Setting(ScoreBoard.Operator.Llama.KeyControl.StopJam)" : "w",
    "ScoreBoard.Settings.Setting(ScoreBoard.Operator.Llama.KeyControl.Team1Lead)" : "x",
    "ScoreBoard.Settings.Setting(ScoreBoard.Operator.Llama.KeyControl.Team1NI)" : "z",
    "ScoreBoard.Settings.Setting(ScoreBoard.Operator.Llama.KeyControl.Team1TripScore4)" : "s",
    "ScoreBoard.Settings.Setting(ScoreBoard.Operator.Llama.KeyControl.Team2Lead)" : "c",
    "ScoreBoard.Settings.Setting(ScoreBoard.Operator.Llama.KeyControl.Team2NI)" : "v",
    "ScoreBoard.Settings.Setting(ScoreBoard.Operator.Llama.KeyControl.Team2TripScore4)" : "d",
    "ScoreBoard.Settings.Setting(ScoreBoard.Operator.Llama.KeyControl.Timeout)" : "e",
    "ScoreBoard.Version(release)" : "v2025.7",
    "ScoreBoard.Version(release.commit)" : "2fb0d8aedc355edc680dc59e375764946edaca2c",
    "ScoreBoard.Version(release.host)" : "localhost",
    "ScoreBoard.Version(release.time)" : "20240526154622",
    "ScoreBoard.Version(release.user)" : "frank"
  }
}